{
  "items": [
    {
      "url": "https://www.wycad.com/259.html",
      "text": "酷我音乐APP v12.1.6.0 去广告破解豪华VIP版",
      "source": "网赚",
      "time": "2026-06-14 17:50:07"
    },
    {
      "url": "https://www.wycad.com/312.html",
      "text": "【不忘初心游戏版】Windows11 LTSC2024（26100.8524）X64 无更新 [精简版][3.23G](2026.5.28) 苹果mac字体 推荐13代及以上CPU 游戏、办公、直播",
      "source": "网赚",
      "time": "2026-06-14 17:50:07"
    },
    {
      "url": "https://www.wycad.com/310.html",
      "text": "【不忘初心游戏版】Windows11 24H2（26100.8524）X64 无更新[精简版][3.32G](2026.5.28) 苹果mac字体 推荐13-15代CPU 游戏、办公、直播",
      "source": "网赚",
      "time": "2026-06-14 17:50:07"
    },
    {
      "url": "https://www.wycad.com/1825.html",
      "text": "Autodesk AutoCAD 2026.1.1 简体中文破解版本",
      "source": "网赚",
      "time": "2026-06-14 17:50:07"
    },
    {
      "url": "https://www.wycad.com/3882.html",
      "text": "Adobe全家桶破解版 2026 CHS-ENG v1 m0nkrus中文直装版",
      "source": "网赚",
      "time": "2026-06-14 17:50:07"
    },
    {
      "url": "https://www.wycad.com/431.html",
      "text": "Adobe Photoshop 2025 v26.11.0.18 中文直装破解版",
      "source": "网赚",
      "time": "2026-06-14 17:50:07"
    },
    {
      "url": "https://www.wycad.com/3570.html",
      "text": "【不忘初心游戏版】Windows11 26H1（28000.2179）X64 无更新[精简版][3.22G](2026.5.30) 苹果mac字体 建议Ultra系列CPU或同级别 游戏、办公、直播",
      "source": "网赚",
      "time": "2026-06-14 17:50:07"
    },
    {
      "url": "https://www.wycad.com/3572.html",
      "text": "【不忘初心】Windows11 26H1（28000.2179）X64 纯净[深度精简版][1.71G](2026.5.30)",
      "source": "网赚",
      "time": "2026-06-14 17:50:07"
    },
    {
      "url": "https://www.wycad.com/3115.html",
      "text": "【不忘初心】Windows11 25H2（26200.8524）X64 纯净[深度精简版][1.64G](2026.5.29)",
      "source": "网赚",
      "time": "2026-06-14 17:50:07"
    },
    {
      "url": "https://www.wycad.com/1075.html",
      "text": "小修 Windows 11 IoT LTSC2024 26200.8655 极限精简版 [1.74G](20260612)",
      "source": "网赚",
      "time": "2026-06-14 17:50:07"
    },
    {
      "url": "https://www.wycad.com/1026.html",
      "text": "小修 Windows 10 LTSC_2019 17763.8880 轻度精简 [1.54G][20260612]",
      "source": "网赚",
      "time": "2026-06-14 17:50:07"
    },
    {
      "url": "https://www.wycad.com/1022.html",
      "text": "小修 Windows 10 LTSC_2019 17763.8880 深度精简 [1.34G][20260612]",
      "source": "网赚",
      "time": "2026-06-14 17:50:07"
    },
    {
      "url": "https://www.wycad.com/4053.html",
      "text": "Windows 11 26H1 28000.2269 RTM 集成更新镜像21in1(2026年6月)",
      "source": "网赚",
      "time": "2026-06-14 17:50:07",
      "category": null
    },
    {
      "url": "https://www.wycad.com/2801.html",
      "text": "Windows 11 23H2 22631.7219 RTM 集成更新镜像20in1  (2026年6月)",
      "source": "网赚",
      "time": "2026-06-14 17:50:07",
      "category": null
    },
    {
      "url": "https://www.wycad.com/1046.html",
      "text": "Windows 10 22H2 19045.7417 RTM 集成更新镜像22in1(2026年06月)",
      "source": "网赚",
      "time": "2026-06-14 17:50:07",
      "category": null
    },
    {
      "url": "https://www.wycad.com/4420.html",
      "text": "7Zip压缩软件 | 7-Zip ZS(多样压缩算法) 26.01 v1.5.7 Release 1 简体中文版",
      "source": "网赚",
      "time": "2026-06-14 17:50:07",
      "category": null
    },
    {
      "url": "https://www.wycad.com/3021.html",
      "text": "无损图片放大工具 | Topaz Gigapixel Pro v1.3.1  破解绿色便携版",
      "source": "网赚",
      "time": "2026-06-14 17:50:07",
      "category": null
    },
    {
      "url": "https://www.wycad.com/3018.html",
      "text": "Ai图片降噪软件 | Topaz Photo Pro v1.6.1 破解汉化绿色版",
      "source": "网赚",
      "time": "2026-06-14 17:50:07",
      "category": null
    },
    {
      "url": "https://www.wycad.com/962.html",
      "text": "文件比较工具 | ExamDiff Pro v17.0.1.2 便携版 (禁止检查更新)",
      "source": "网赚",
      "time": "2026-06-14 17:50:07",
      "category": null
    },
    {
      "url": "https://www.wycad.com/588.html",
      "text": "冰凌五笔输入法 v13.8.6.260615 蕤宾版",
      "source": "网赚",
      "time": "2026-06-14 17:50:07",
      "category": null
    },
    {
      "url": "https://www.wycad.com/1459.html",
      "text": "开源电子书阅读器 | Koodo Reader v2.3.6 中文绿色版",
      "source": "网赚",
      "time": "2026-06-14 17:50:07",
      "category": null
    },
    {
      "url": "https://www.wycad.com/423.html",
      "text": "图像扫描软件 | VueScan Pro v9.8.55 中文破解绿色版",
      "source": "网赚",
      "time": "2026-06-14 17:50:07"
    },
    {
      "url": "https://www.wycad.com/78.html",
      "text": "【不忘初心游戏版】[太阳谷] Windows10 22H2（19045.7291） X64 无更新[精简版][2.98G](2026.5.13) 苹果mac字体 推荐7-11代CPU 游戏、办公、直播",
      "source": "网赚",
      "time": "2026-06-14 17:50:07"
    },
    {
      "url": "https://www.wycad.com/1279.html",
      "text": "【不忘初心游戏版】[太阳谷] Windows10 LTSC2021（19044.7291）X64 无更新[精简版][3.02G](2026.5.13) 建议3-11代CPU",
      "source": "网赚",
      "time": "2026-06-14 17:50:07"
    },
    {
      "url": "https://www.wycad.com/567.html",
      "text": "WPS Office 2023专业增强版 v12.8.2.26375永久激活版(06.08)",
      "source": "网赚",
      "time": "2026-06-14 17:50:07"
    },
    {
      "url": "https://www.wycad.com/88.html",
      "text": "【不忘初心】Windows10 22H2（19045.7291）X64 纯净[深度精简版][1.45G](2026.5.13)",
      "source": "网赚",
      "time": "2026-06-14 17:50:07"
    },
    {
      "url": "https://www.wycad.com/306.html",
      "text": "【不忘初心游戏版】Windows11 23H2（22631.7079）X64 无更新[精简版][3.34G](2026.5.16) 苹果mac字体 推荐12-14代CPU 游戏、直播、办公",
      "source": "网赚",
      "time": "2026-06-14 17:50:07"
    },
    {
      "url": "https://www.wycad.com/84.html",
      "text": "小修 Windows 10 LTSC2021 19044.7417 极限精简版 [1.52G](20260611)",
      "source": "网赚",
      "time": "2026-06-14 17:50:07"
    },
    {
      "url": "https://www.wycad.com/1000.html",
      "text": "小修 Windows 11 23H2 22631.7219 稳定精简 极限版 [1.61G] (20260610)",
      "source": "网赚",
      "time": "2026-06-14 17:50:07"
    },
    {
      "url": "https://www.wycad.com/1001.html",
      "text": "小修 Windows 11 23H2 22631.7219 轻度精简版 [1.73G] (20260610)",
      "source": "网赚",
      "time": "2026-06-14 17:50:07"
    },
    {
      "url": "https://news.ixbk.net/category-guanzhu1/",
      "text": "我的关注",
      "source": "线报酷",
      "time": "2026-06-14 17:50:07"
    },
    {
      "url": "https://news.ixbk.net/zuankeba-hot.html",
      "text": "赚客吧热帖",
      "source": "线报酷",
      "time": "2026-06-14 17:50:07"
    },
    {
      "url": "https://news.ixbk.net/xinzuanba-hot.html",
      "text": "新赚吧热帖",
      "source": "线报酷",
      "time": "2026-06-14 17:50:07"
    },
    {
      "url": "https://news.ixbk.net/category-douban/",
      "text": "豆瓣线报",
      "source": "线报酷",
      "time": "2026-06-14 17:50:07"
    },
    {
      "url": "https://news.ixbk.net/douban-hot.html",
      "text": "豆瓣热帖",
      "source": "线报酷",
      "time": "2026-06-14 17:50:07"
    },
    {
      "url": "https://news.ixbk.net/category-weibo/",
      "text": "微博线报",
      "source": "线报酷",
      "time": "2026-06-14 17:50:07"
    },
    {
      "url": "https://news.ixbk.net/category-weibo-chaohua/",
      "text": "微博超话",
      "source": "线报酷",
      "time": "2026-06-14 17:50:07"
    },
    {
      "url": "https://news.ixbk.net/weibo-hot.html",
      "text": "微博热帖",
      "source": "线报酷",
      "time": "2026-06-14 17:50:07"
    },
    {
      "url": "https://news.ixbk.net/category-haodan/",
      "text": "好单线报",
      "source": "线报酷",
      "time": "2026-06-14 17:50:07"
    },
    {
      "url": "https://news.ixbk.net/zhidemai-hot.html",
      "text": "值得买热帖",
      "source": "线报酷",
      "time": "2026-06-14 17:50:07"
    },
    {
      "url": "https://news.ixbk.net/category-huluxia/",
      "text": "葫芦侠三楼",
      "source": "线报酷",
      "time": "2026-06-14 17:50:07"
    },
    {
      "url": "https://news.ixbk.net/category-man/",
      "text": "更新较慢活动",
      "source": "线报酷",
      "time": "2026-06-14 17:50:07"
    },
    {
      "url": "https://news.ixbk.net/category-xiaodao/",
      "text": "小刀娱乐网",
      "source": "线报酷",
      "time": "2026-06-14 17:50:07"
    },
    {
      "url": "https://news.ixbk.net/category-iqnew/",
      "text": "爱Q生活网",
      "source": "线报酷",
      "time": "2026-06-14 17:50:07"
    },
    {
      "url": "https://news.ixbk.net/category-mianfei/",
      "text": "免费赚钱中心",
      "source": "线报酷",
      "time": "2026-06-14 17:50:07"
    },
    {
      "url": "https://news.ixbk.net/haodan/6459772.html",
      "text": "海尔200升冷柜一级BC/BD-200GHW9D 200L 500元",
      "source": "线报酷",
      "time": "2026-06-14 17:50:07",
      "category": null
    },
    {
      "url": "https://news.ixbk.net/haodan/6459771.html",
      "text": "戴可思电蚊香液1器4液 18.1元",
      "source": "线报酷",
      "time": "2026-06-14 17:50:07",
      "category": null
    },
    {
      "url": "https://news.ixbk.net/haodan/6459770.html",
      "text": "你好中国第1辑全10册 33元",
      "source": "线报酷",
      "time": "2026-06-14 17:50:07",
      "category": null
    },
    {
      "url": "https://news.ixbk.net/weibo/6459769.html",
      "text": "胡姬花古法花生油6.08L*2桶 196元",
      "source": "线报酷",
      "time": "2026-06-14 17:50:07",
      "category": null
    },
    {
      "url": "https://news.ixbk.net/haodan/6459767.html",
      "text": "自由点安心裤卫生巾组合30片 21.2元",
      "source": "线报酷",
      "time": "2026-06-14 17:50:07",
      "category": null
    },
    {
      "url": "https://news.ixbk.net/haodan/6459766.html",
      "text": "芥大侠开味酸菜150g*2瓶 9.9元",
      "source": "线报酷",
      "time": "2026-06-14 17:50:07",
      "category": null
    },
    {
      "url": "https://news.ixbk.net/haodan/6459764.html",
      "text": "圣农超大个鸡翅中嘟嘟翅280g*6包 99.9元",
      "source": "线报酷",
      "time": "2026-06-14 17:50:07",
      "category": null
    },
    {
      "url": "https://news.ixbk.net/haodan/6459763.html",
      "text": "碧然德环保加固包装过滤净水器蓝色 158.4元",
      "source": "线报酷",
      "time": "2026-06-14 17:50:07",
      "category": null
    },
    {
      "url": "https://news.ixbk.net/haodan/6459762.html",
      "text": "喵洁客膨润土猫砂蓝标42磅 99.5元",
      "source": "线报酷",
      "time": "2026-06-14 17:50:07",
      "category": null
    },
    {
      "url": "https://news.ixbk.net/haodan/6459765.html",
      "text": "生生不息鸭肉主食冻干400g 169元",
      "source": "线报酷",
      "time": "2026-06-14 17:50:07",
      "category": null
    },
    {
      "url": "https://news.ixbk.net/haodan/6459761.html",
      "text": "iQOO 15T手机传奇版16+512G 3749元",
      "source": "线报酷",
      "time": "2026-06-14 17:50:07",
      "category": null
    },
    {
      "url": "https://news.ixbk.net/haodan/6459760.html",
      "text": "绽妍透明质酸修护生物敷料150ml透明质酸修护喷雾2瓶 88.3元",
      "source": "线报酷",
      "time": "2026-06-14 17:50:07",
      "category": null
    },
    {
      "url": "https://news.ixbk.net/weibo-chaohua/6459757.html",
      "text": "kfm好价吗",
      "source": "线报酷",
      "time": "2026-06-14 17:50:07",
      "category": null
    },
    {
      "url": "https://news.ixbk.net/haodan/6459759.html",
      "text": "追觅S50增强版扫地机器人超薄上下水版 2308.68元",
      "source": "线报酷",
      "time": "2026-06-14 17:50:07",
      "category": null
    },
    {
      "url": "https://news.ixbk.net/haodan/6459758.html",
      "text": "十月结晶婴儿包单85*85cm 17.8元",
      "source": "线报酷",
      "time": "2026-06-14 17:50:07",
      "category": null
    },
    {
      "url": "https://news.ixbk.net/haodan/6459756.html",
      "text": "卡姿兰女士雾光粉饼定妆粉 赠粉扑 19.9元",
      "source": "线报酷",
      "time": "2026-06-14 17:50:07",
      "category": null
    },
    {
      "url": "https://news.ixbk.net/haodan/6459754.html",
      "text": "桂格人参燕麦粉礼盒500g*2罐 26元",
      "source": "线报酷",
      "time": "2026-06-14 17:50:07",
      "category": null
    },
    {
      "url": "https://news.ixbk.net/haodan/6459753.html",
      "text": "思念云吞饺子合集任选10件 59元",
      "source": "线报酷",
      "time": "2026-06-14 17:50:07",
      "category": null
    },
    {
      "url": "https://news.ixbk.net/weibo/6459752.html",
      "text": "基诺浦儿童软底透气学步凉鞋 108.9元",
      "source": "线报酷",
      "time": "2026-06-14 17:50:07",
      "category": null
    },
    {
      "url": "https://news.ixbk.net/haodan/6459751.html",
      "text": "真真老老粽子礼盒8粽6味1180g 22.9元",
      "source": "线报酷",
      "time": "2026-06-14 17:50:07",
      "category": null
    },
    {
      "url": "https://news.ixbk.net/haodan/6459750.html",
      "text": "佳帮手海绵拖把28cm 1加厚棉头 14.8元，佳帮手免手洗平板拖把35cm 2块布 14.8元",
      "source": "线报酷",
      "time": "2026-06-14 17:50:07",
      "category": null
    },
    {
      "url": "https://news.ixbk.net/weibo-chaohua/6459749.html",
      "text": "请问你们知道xhs老活动吗",
      "source": "线报酷",
      "time": "2026-06-14 17:50:07",
      "category": null
    },
    {
      "url": "https://news.ixbk.net/haodan/6459748.html",
      "text": "京东plus年卡 39元",
      "source": "线报酷",
      "time": "2026-06-14 17:50:07",
      "category": "京东"
    },
    {
      "url": "https://news.ixbk.net/haodan/6459746.html",
      "text": "飞鹤中老年多维奶粉700g*2 79元，飞鹤高钙多维奶粉700g*2 88元",
      "source": "线报酷",
      "time": "2026-06-14 17:50:07",
      "category": null
    },
    {
      "url": "https://news.ixbk.net/haodan/6459745.html",
      "text": "维他奶巧克力豆奶250ml*16盒 25.2元",
      "source": "线报酷",
      "time": "2026-06-14 17:50:07",
      "category": null
    },
    {
      "url": "https://news.ixbk.net/weibo/6459768.html",
      "text": "先领60-10亓补贴卷 再右上角叠🍑金币加购 凑消费卷",
      "source": "线报酷",
      "time": "2026-06-14 17:50:07",
      "category": null
    },
    {
      "url": "https://news.ixbk.net/zuankeba/6459747.html",
      "text": "微信红包，江苏",
      "source": "线报酷",
      "time": "2026-06-14 17:50:07",
      "category": "红包"
    },
    {
      "url": "https://news.ixbk.net/xiaodigu/6459744.html",
      "text": "卡卡广东 下拉点二维码",
      "source": "线报酷",
      "time": "2026-06-14 17:50:07",
      "category": null
    },
    {
      "url": "https://news.ixbk.net/haodan/6459743.html",
      "text": "卡奇尔维D2磷葡钙片84片装 88.8元",
      "source": "线报酷",
      "time": "2026-06-14 17:50:07",
      "category": null
    },
    {
      "url": "https://news.ixbk.net/haodan/6459741.html",
      "text": "珀莱雅双抗精华100ml 189元",
      "source": "线报酷",
      "time": "2026-06-14 17:50:07",
      "category": null
    },
    {
      "url": "https://news.ixbk.net/zuankeba/6459742.html",
      "text": "全返冰袖",
      "source": "线报酷",
      "time": "2026-06-14 17:50:07",
      "category": null
    },
    {
      "url": "https://news.ixbk.net/haodan/6459740.html",
      "text": "领先鸭肉梨烘焙狗粮200g 6.9元",
      "source": "线报酷",
      "time": "2026-06-14 17:50:07",
      "category": null
    },
    {
      "url": "https://news.ixbk.net/haodan/6459738.html",
      "text": "乐比叮婴儿驱蚊喷雾100ml/瓶 19.8元",
      "source": "线报酷",
      "time": "2026-06-14 17:50:07",
      "category": null
    },
    {
      "url": "https://news.ixbk.net/haodan/6459739.html",
      "text": "云朵季大包抽纸5层400张*20包 24.9元",
      "source": "线报酷",
      "time": "2026-06-14 17:50:07",
      "category": null
    },
    {
      "url": "https://news.ixbk.net/weibo/6459737.html",
      "text": "1$v5zc5rmf60Y$:/ CZ6135 或复制淘囗令打开手机淘宝",
      "source": "线报酷",
      "time": "2026-06-14 17:50:07",
      "category": "淘宝"
    },
    {
      "url": "https://news.ixbk.fun/category-guanzhu1/",
      "text": "我的关注",
      "source": "线报酷",
      "time": "2026-06-14 17:50:07"
    },
    {
      "url": "https://news.ixbk.fun/zuankeba-hot.html",
      "text": "赚客吧热帖",
      "source": "线报酷",
      "time": "2026-06-14 17:50:07"
    },
    {
      "url": "https://news.ixbk.fun/xinzuanba-hot.html",
      "text": "新赚吧热帖",
      "source": "线报酷",
      "time": "2026-06-14 17:50:07"
    },
    {
      "url": "https://news.ixbk.fun/category-douban/",
      "text": "豆瓣线报",
      "source": "线报酷",
      "time": "2026-06-14 17:50:07"
    },
    {
      "url": "https://news.ixbk.fun/douban-hot.html",
      "text": "豆瓣热帖",
      "source": "线报酷",
      "time": "2026-06-14 17:50:07"
    },
    {
      "url": "https://news.ixbk.fun/category-weibo/",
      "text": "微博线报",
      "source": "线报酷",
      "time": "2026-06-14 17:50:07"
    },
    {
      "url": "https://news.ixbk.fun/category-weibo-chaohua/",
      "text": "微博超话",
      "source": "线报酷",
      "time": "2026-06-14 17:50:07"
    },
    {
      "url": "https://news.ixbk.fun/weibo-hot.html",
      "text": "微博热帖",
      "source": "线报酷",
      "time": "2026-06-14 17:50:07"
    },
    {
      "url": "https://news.ixbk.fun/category-haodan/",
      "text": "好单线报",
      "source": "线报酷",
      "time": "2026-06-14 17:50:07"
    },
    {
      "url": "https://news.ixbk.fun/zhidemai-hot.html",
      "text": "值得买热帖",
      "source": "线报酷",
      "time": "2026-06-14 17:50:07"
    },
    {
      "url": "https://news.ixbk.fun/category-huluxia/",
      "text": "葫芦侠三楼",
      "source": "线报酷",
      "time": "2026-06-14 17:50:07"
    },
    {
      "url": "https://news.ixbk.fun/category-man/",
      "text": "更新较慢活动",
      "source": "线报酷",
      "time": "2026-06-14 17:50:07"
    },
    {
      "url": "https://news.ixbk.fun/category-xiaodao/",
      "text": "小刀娱乐网",
      "source": "线报酷",
      "time": "2026-06-14 17:50:07"
    },
    {
      "url": "https://news.ixbk.fun/category-iqnew/",
      "text": "爱Q生活网",
      "source": "线报酷",
      "time": "2026-06-14 17:50:07"
    },
    {
      "url": "https://news.ixbk.fun/category-mianfei/",
      "text": "免费赚钱中心",
      "source": "线报酷",
      "time": "2026-06-14 17:50:07"
    },
    {
      "url": "https://news.ixbk.fun/haodan/6459772.html",
      "text": "海尔200升冷柜一级BC/BD-200GHW9D 200L 500元",
      "source": "线报酷",
      "time": "2026-06-14 17:50:07",
      "category": null
    },
    {
      "url": "https://news.ixbk.fun/haodan/6459771.html",
      "text": "戴可思电蚊香液1器4液 18.1元",
      "source": "线报酷",
      "time": "2026-06-14 17:50:07",
      "category": null
    },
    {
      "url": "https://news.ixbk.fun/haodan/6459770.html",
      "text": "你好中国第1辑全10册 33元",
      "source": "线报酷",
      "time": "2026-06-14 17:50:07",
      "category": null
    },
    {
      "url": "https://news.ixbk.fun/weibo/6459769.html",
      "text": "胡姬花古法花生油6.08L*2桶 196元",
      "source": "线报酷",
      "time": "2026-06-14 17:50:07",
      "category": null
    },
    {
      "url": "https://news.ixbk.fun/haodan/6459767.html",
      "text": "自由点安心裤卫生巾组合30片 21.2元",
      "source": "线报酷",
      "time": "2026-06-14 17:50:07",
      "category": null
    },
    {
      "url": "https://news.ixbk.fun/haodan/6459766.html",
      "text": "芥大侠开味酸菜150g*2瓶 9.9元",
      "source": "线报酷",
      "time": "2026-06-14 17:50:07",
      "category": null
    },
    {
      "url": "https://news.ixbk.fun/haodan/6459764.html",
      "text": "圣农超大个鸡翅中嘟嘟翅280g*6包 99.9元",
      "source": "线报酷",
      "time": "2026-06-14 17:50:07",
      "category": null
    },
    {
      "url": "https://news.ixbk.fun/haodan/6459763.html",
      "text": "碧然德环保加固包装过滤净水器蓝色 158.4元",
      "source": "线报酷",
      "time": "2026-06-14 17:50:07",
      "category": null
    },
    {
      "url": "https://news.ixbk.fun/haodan/6459762.html",
      "text": "喵洁客膨润土猫砂蓝标42磅 99.5元",
      "source": "线报酷",
      "time": "2026-06-14 17:50:07",
      "category": null
    },
    {
      "url": "https://news.ixbk.fun/haodan/6459765.html",
      "text": "生生不息鸭肉主食冻干400g 169元",
      "source": "线报酷",
      "time": "2026-06-14 17:50:07",
      "category": null
    },
    {
      "url": "https://news.ixbk.fun/haodan/6459761.html",
      "text": "iQOO 15T手机传奇版16+512G 3749元",
      "source": "线报酷",
      "time": "2026-06-14 17:50:07",
      "category": null
    },
    {
      "url": "https://news.ixbk.fun/haodan/6459760.html",
      "text": "绽妍透明质酸修护生物敷料150ml透明质酸修护喷雾2瓶 88.3元",
      "source": "线报酷",
      "time": "2026-06-14 17:50:07",
      "category": null
    },
    {
      "url": "https://news.ixbk.fun/weibo-chaohua/6459757.html",
      "text": "kfm好价吗",
      "source": "线报酷",
      "time": "2026-06-14 17:50:07",
      "category": null
    },
    {
      "url": "https://news.ixbk.fun/haodan/6459759.html",
      "text": "追觅S50增强版扫地机器人超薄上下水版 2308.68元",
      "source": "线报酷",
      "time": "2026-06-14 17:50:07",
      "category": null
    },
    {
      "url": "https://news.ixbk.fun/haodan/6459758.html",
      "text": "十月结晶婴儿包单85*85cm 17.8元",
      "source": "线报酷",
      "time": "2026-06-14 17:50:07",
      "category": null
    },
    {
      "url": "https://news.ixbk.fun/haodan/6459756.html",
      "text": "卡姿兰女士雾光粉饼定妆粉 赠粉扑 19.9元",
      "source": "线报酷",
      "time": "2026-06-14 17:50:07",
      "category": null
    },
    {
      "url": "https://news.ixbk.fun/haodan/6459754.html",
      "text": "桂格人参燕麦粉礼盒500g*2罐 26元",
      "source": "线报酷",
      "time": "2026-06-14 17:50:07",
      "category": null
    },
    {
      "url": "https://news.ixbk.fun/haodan/6459753.html",
      "text": "思念云吞饺子合集任选10件 59元",
      "source": "线报酷",
      "time": "2026-06-14 17:50:07",
      "category": null
    },
    {
      "url": "https://news.ixbk.fun/weibo/6459752.html",
      "text": "基诺浦儿童软底透气学步凉鞋 108.9元",
      "source": "线报酷",
      "time": "2026-06-14 17:50:07",
      "category": null
    },
    {
      "url": "https://news.ixbk.fun/haodan/6459751.html",
      "text": "真真老老粽子礼盒8粽6味1180g 22.9元",
      "source": "线报酷",
      "time": "2026-06-14 17:50:07",
      "category": null
    },
    {
      "url": "https://news.ixbk.fun/haodan/6459750.html",
      "text": "佳帮手海绵拖把28cm 1加厚棉头 14.8元，佳帮手免手洗平板拖把35cm 2块布 14.8元",
      "source": "线报酷",
      "time": "2026-06-14 17:50:07",
      "category": null
    },
    {
      "url": "https://news.ixbk.fun/weibo-chaohua/6459749.html",
      "text": "请问你们知道xhs老活动吗",
      "source": "线报酷",
      "time": "2026-06-14 17:50:07",
      "category": null
    },
    {
      "url": "https://news.ixbk.fun/haodan/6459748.html",
      "text": "京东plus年卡 39元",
      "source": "线报酷",
      "time": "2026-06-14 17:50:07",
      "category": "京东"
    },
    {
      "url": "https://news.ixbk.fun/haodan/6459746.html",
      "text": "飞鹤中老年多维奶粉700g*2 79元，飞鹤高钙多维奶粉700g*2 88元",
      "source": "线报酷",
      "time": "2026-06-14 17:50:07",
      "category": null
    },
    {
      "url": "https://news.ixbk.fun/haodan/6459745.html",
      "text": "维他奶巧克力豆奶250ml*16盒 25.2元",
      "source": "线报酷",
      "time": "2026-06-14 17:50:07",
      "category": null
    },
    {
      "url": "https://news.ixbk.fun/weibo/6459768.html",
      "text": "先领60-10亓补贴卷 再右上角叠🍑金币加购 凑消费卷",
      "source": "线报酷",
      "time": "2026-06-14 17:50:07",
      "category": null
    },
    {
      "url": "https://news.ixbk.fun/zuankeba/6459747.html",
      "text": "微信红包，江苏",
      "source": "线报酷",
      "time": "2026-06-14 17:50:07",
      "category": "红包"
    },
    {
      "url": "https://news.ixbk.fun/xiaodigu/6459744.html",
      "text": "卡卡广东 下拉点二维码",
      "source": "线报酷",
      "time": "2026-06-14 17:50:07",
      "category": null
    },
    {
      "url": "https://news.ixbk.fun/haodan/6459743.html",
      "text": "卡奇尔维D2磷葡钙片84片装 88.8元",
      "source": "线报酷",
      "time": "2026-06-14 17:50:07",
      "category": null
    },
    {
      "url": "https://news.ixbk.fun/haodan/6459741.html",
      "text": "珀莱雅双抗精华100ml 189元",
      "source": "线报酷",
      "time": "2026-06-14 17:50:07",
      "category": null
    },
    {
      "url": "https://news.ixbk.fun/zuankeba/6459742.html",
      "text": "全返冰袖",
      "source": "线报酷",
      "time": "2026-06-14 17:50:07",
      "category": null
    },
    {
      "url": "https://news.ixbk.fun/haodan/6459740.html",
      "text": "领先鸭肉梨烘焙狗粮200g 6.9元",
      "source": "线报酷",
      "time": "2026-06-14 17:50:07",
      "category": null
    },
    {
      "url": "https://news.ixbk.fun/haodan/6459738.html",
      "text": "乐比叮婴儿驱蚊喷雾100ml/瓶 19.8元",
      "source": "线报酷",
      "time": "2026-06-14 17:50:07",
      "category": null
    },
    {
      "url": "https://news.ixbk.fun/haodan/6459739.html",
      "text": "云朵季大包抽纸5层400张*20包 24.9元",
      "source": "线报酷",
      "time": "2026-06-14 17:50:07",
      "category": null
    },
    {
      "url": "https://news.ixbk.fun/weibo/6459737.html",
      "text": "1$v5zc5rmf60Y$:/ CZ6135 或复制淘囗令打开手机淘宝",
      "source": "线报酷",
      "time": "2026-06-14 17:50:07",
      "category": "淘宝"
    },
    {
      "url": "https://v1.xianbao.net/member.php?mod=register",
      "text": "立即注册",
      "source": "线报网",
      "time": "2026-06-14 17:50:07"
    },
    {
      "url": "https://v1.xianbao.net/app.php?p=account&action=security&op=resetpassword",
      "text": "找回密码",
      "source": "线报网",
      "time": "2026-06-14 17:50:07"
    },
    {
      "url": "https://v1.xianbao.net/misc.php?mod=faq",
      "text": "帮助Help",
      "source": "线报网",
      "time": "2026-06-14 17:50:07"
    },
    {
      "url": "https://v1.xianbao.net/forum.php?mod=collection",
      "text": "淘帖Collection",
      "source": "线报网",
      "time": "2026-06-14 17:50:07"
    },
    {
      "url": "https://v1.xianbao.net/misc.php?mod=ranklist",
      "text": "排行榜Ranklist",
      "source": "线报网",
      "time": "2026-06-14 17:50:07"
    },
    {
      "url": "https://v1.xianbao.net/plugin.php?id=dsu_paulsign:sign",
      "text": "每日签到",
      "source": "线报网",
      "time": "2026-06-14 17:50:07"
    },
    {
      "url": "https://v1.xianbao.net/oauth.php?action=freeinvitecode",
      "text": "智能自助服务导航",
      "source": "线报网",
      "time": "2026-06-14 17:50:07"
    },
    {
      "url": "https://v1.xianbao.net/forum-42-1.html",
      "text": "果果换物 [新上线]",
      "source": "线报网",
      "time": "2026-06-14 17:50:07"
    },
    {
      "url": "https://v1.xianbao.net/app.php?p=invite&action=invitecode",
      "text": "邀请好友注册",
      "source": "线报网",
      "time": "2026-06-14 17:50:07"
    },
    {
      "url": "https://v1.xianbao.net/thread-24783-1-1.html",
      "text": "新手入门指南",
      "source": "线报网",
      "time": "2026-06-14 17:50:07"
    },
    {
      "url": "https://v1.xianbao.net/forum-41-1.html",
      "text": "做任务赚果果",
      "source": "线报网",
      "time": "2026-06-14 17:50:07"
    },
    {
      "url": "https://v1.xianbao.net/forum-2-1.html",
      "text": "赚客大家谈",
      "source": "线报网",
      "time": "2026-06-14 17:50:07"
    },
    {
      "url": "https://v1.xianbao.net/forum-36-1.html",
      "text": "赚品交换",
      "source": "线报网",
      "time": "2026-06-14 17:50:07"
    },
    {
      "url": "https://v1.xianbao.net/forum-37-1.html",
      "text": "邀请专区",
      "source": "线报网",
      "time": "2026-06-14 17:50:07"
    },
    {
      "url": "https://v1.xianbao.net/forum-38-1.html",
      "text": "吧务/建议",
      "source": "线报网",
      "time": "2026-06-14 17:50:07"
    },
    {
      "url": "https://v1.xianbao.net/new.php",
      "text": "【最新主题】",
      "source": "线报网",
      "time": "2026-06-14 17:50:07"
    },
    {
      "url": "https://v1.xianbao.net/app.php?p=page&action=hot",
      "text": "【新版热帖】",
      "source": "线报网",
      "time": "2026-06-14 17:50:07"
    },
    {
      "url": "https://v1.xianbao.net/re.php",
      "text": "【老版热帖】",
      "source": "线报网",
      "time": "2026-06-14 17:50:07"
    },
    {
      "url": "https://v1.xianbao.net/app.php?p=threadday&action=thread",
      "text": "【天天线报】主题排名榜",
      "source": "线报网",
      "time": "2026-06-14 17:50:07"
    },
    {
      "url": "https://v1.xianbao.net/misc.php?mod=ranklist&type=thread&view=replies&orderby=thisweek",
      "text": "【排名榜】回复排名榜",
      "source": "线报网",
      "time": "2026-06-14 17:50:07"
    },
    {
      "url": "https://v1.xianbao.net/forum.php?mod=post&action=newthread&fid=2",
      "text": "【快速发帖】",
      "source": "线报网",
      "time": "2026-06-14 17:50:07"
    },
    {
      "url": "https://v1.xianbao.net/thread-24300-1-1.html",
      "text": "【学习规则以及常见问题】",
      "source": "线报网",
      "time": "2026-06-14 17:50:07"
    },
    {
      "url": "https://v1.xianbao.net/thread-24934-1-1.html",
      "text": "【活动】天天线报",
      "source": "线报网",
      "time": "2026-06-14 17:50:07"
    },
    {
      "url": "https://v1.xianbao.net/forum-48-1.html",
      "text": "【活动】周日抢楼",
      "source": "线报网",
      "time": "2026-06-14 17:50:07"
    },
    {
      "url": "https://v1.xianbao.net/thread-21073-1-1.html",
      "text": "【活动】线报大赛",
      "source": "线报网",
      "time": "2026-06-14 17:50:07"
    },
    {
      "url": "https://v1.xianbao.net/app.php?p=threadday",
      "text": "天天线报",
      "source": "线报网",
      "time": "2026-06-14 17:50:07"
    },
    {
      "url": "https://v1.xianbao.net/app.php?p=threadrush",
      "text": "抢楼奖励",
      "source": "线报网",
      "time": "2026-06-14 17:50:07"
    },
    {
      "url": "https://v1.xianbao.net/app.php?p=invite&action=invitecode",
      "text": "邀请奖励",
      "source": "线报网",
      "time": "2026-06-14 17:50:07"
    },
    {
      "url": "https://www.yuque.com/xiaoen-lfhtn/xianbao/ux20ikrol44i8ysz",
      "text": "👉 加入官方Q群 免费注册",
      "source": "线报网",
      "time": "2026-06-14 17:50:07"
    },
    {
      "url": "https://v1.xianbao.net/thread-30634-1-1.html",
      "text": "线报酷YYDS",
      "source": "线报网",
      "time": "2026-06-14 17:50:07"
    },
    {
      "url": "https://v1.xianbao.net/space-username-%E7%82%B8%E8%A5%BF%E7%9A%84%E4%B9%90.html",
      "text": "炸西的乐",
      "source": "线报网",
      "time": "2026-06-14 17:50:07"
    },
    {
      "url": "https://v1.xianbao.net/forum.php?mod=guide&view=new",
      "text": "最新回复",
      "source": "线报网",
      "time": "2026-06-14 17:50:07"
    },
    {
      "url": "https://v1.xianbao.net/forum.php?gid=1",
      "text": "有你更精彩",
      "source": "线报网",
      "time": "2026-06-14 17:50:07"
    },
    {
      "url": "https://v1.xianbao.net/forum.php?mod=redirect&tid=310181&goto=lastpost#lastpost",
      "text": "预算1千以内的二手苹果机，最优 ...",
      "source": "线报网",
      "time": "2026-06-14 17:50:07"
    },
    {
      "url": "https://v1.xianbao.net/space-username-%E6%97%A0%E6%9E%81%E7%A7%91%E6%8A%80.html",
      "text": "无极科技",
      "source": "线报网",
      "time": "2026-06-14 17:50:07",
      "category": null
    },
    {
      "url": "https://v1.xianbao.net/forum-50-1.html",
      "text": "发现与探索",
      "source": "线报网",
      "time": "2026-06-14 17:50:07"
    },
    {
      "url": "https://v1.xianbao.net/forum-39-1.html",
      "text": "悬赏问问",
      "source": "线报网",
      "time": "2026-06-14 17:50:07"
    },
    {
      "url": "https://v1.xianbao.net/forum.php?gid=53",
      "text": "果果权益区",
      "source": "线报网",
      "time": "2026-06-14 17:50:07"
    },
    {
      "url": "https://v1.xianbao.net/forum-42-1.html",
      "text": "果果换物",
      "source": "线报网",
      "time": "2026-06-14 17:50:07"
    },
    {
      "url": "https://v1.xianbao.net/forum-57-1.html",
      "text": "押果交易",
      "source": "线报网",
      "time": "2026-06-14 17:50:07"
    },
    {
      "url": "https://v1.xianbao.net/forum.php?gid=54",
      "text": "论坛事务区",
      "source": "线报网",
      "time": "2026-06-14 17:50:07"
    },
    {
      "url": "https://v1.xianbao.net/forum-38-1.html",
      "text": "吧务/建议/投诉",
      "source": "线报网",
      "time": "2026-06-14 17:50:07"
    },
    {
      "url": "https://v1.xianbao.net/forum-47-1.html",
      "text": "论坛规则学习",
      "source": "线报网",
      "time": "2026-06-14 17:50:07"
    },
    {
      "url": "https://v1.xianbao.net/space-username-lauyuhui.html",
      "text": "lauyuhui",
      "source": "线报网",
      "time": "2026-06-14 17:50:07"
    },
    {
      "url": "https://v1.xianbao.net/forum-52-1.html",
      "text": "自助申请解封 (小黑屋)",
      "source": "线报网",
      "time": "2026-06-14 17:50:07"
    },
    {
      "url": "https://v1.xianbao.net/forum-49-1.html",
      "text": "吧务申请专区",
      "source": "线报网",
      "time": "2026-06-14 17:50:07"
    },
    {
      "url": "https://v1.xianbao.net/forum-46-1.html",
      "text": "老吧友认证区",
      "source": "线报网",
      "time": "2026-06-14 17:50:07"
    },
    {
      "url": "https://v1.xianbao.net/",
      "text": "线报社区",
      "source": "线报网",
      "time": "2026-06-14 17:50:07"
    },
    {
      "url": "https://www.huifabu.cn/#lst",
      "text": "跳转到主要内容",
      "source": "汇发部",
      "time": "2026-06-14 17:50:07"
    },
    {
      "url": "https://www.huifabu.cn/haodan/164000.html",
      "text": "好单海尔200升冷柜一级BC/BD-200GHW9D 200L 500元06-14 17:49›",
      "source": "汇发部",
      "time": "2026-06-14 17:50:07",
      "category": null
    },
    {
      "url": "https://www.huifabu.cn/haodan/163999.html",
      "text": "好单戴可思电蚊香液1器4液 18.1元06-14 17:49›",
      "source": "汇发部",
      "time": "2026-06-14 17:50:07",
      "category": null
    },
    {
      "url": "https://www.huifabu.cn/haodan/163998.html",
      "text": "好单你好中国第1辑全10册 33元06-14 17:49›",
      "source": "汇发部",
      "time": "2026-06-14 17:50:07",
      "category": null
    },
    {
      "url": "https://www.huifabu.cn/weibo/163997.html",
      "text": "微博胡姬花古法花生油6.08L*2桶 196元06-14 17:49›",
      "source": "汇发部",
      "time": "2026-06-14 17:50:07",
      "category": null
    },
    {
      "url": "https://www.huifabu.cn/weibo/163996.html",
      "text": "微博先领60-10亓补贴卷 再右上角叠🍑金币加购 凑消费卷06-14 17:44›",
      "source": "汇发部",
      "time": "2026-06-14 17:50:07",
      "category": null
    },
    {
      "url": "https://www.huifabu.cn/haodan/163995.html",
      "text": "好单自由点安心裤卫生巾组合30片 21.2元06-14 17:48›",
      "source": "汇发部",
      "time": "2026-06-14 17:50:07",
      "category": null
    },
    {
      "url": "https://www.huifabu.cn/haodan/163994.html",
      "text": "好单芥大侠开味酸菜150g*2瓶 9.9元06-14 17:48›",
      "source": "汇发部",
      "time": "2026-06-14 17:50:07",
      "category": null
    },
    {
      "url": "https://www.huifabu.cn/haodan/163993.html",
      "text": "好单生生不息鸭肉主食冻干400g 169元06-14 17:47›",
      "source": "汇发部",
      "time": "2026-06-14 17:50:07",
      "category": null
    },
    {
      "url": "https://www.huifabu.cn/haodan/163992.html",
      "text": "好单圣农超大个鸡翅中嘟嘟翅280g*6包 99.9元06-14 17:48›",
      "source": "汇发部",
      "time": "2026-06-14 17:50:07",
      "category": null
    },
    {
      "url": "https://www.huifabu.cn/haodan/163991.html",
      "text": "好单碧然德环保加固包装过滤净水器蓝色 158.4元06-14 17:48›",
      "source": "汇发部",
      "time": "2026-06-14 17:50:07",
      "category": null
    },
    {
      "url": "https://www.huifabu.cn/haodan/163990.html",
      "text": "好单喵洁客膨润土猫砂蓝标42磅 99.5元06-14 17:47›",
      "source": "汇发部",
      "time": "2026-06-14 17:50:07",
      "category": null
    },
    {
      "url": "https://www.huifabu.cn/haodan/163989.html",
      "text": "好单iQOO 15T手机传奇版16+512G 3749元06-14 17:47›",
      "source": "汇发部",
      "time": "2026-06-14 17:50:07",
      "category": null
    },
    {
      "url": "https://www.huifabu.cn/haodan/163988.html",
      "text": "好单绽妍透明质酸修护生物敷料150ml透明质酸修护喷雾2瓶 88.3元06-14 17:47›",
      "source": "汇发部",
      "time": "2026-06-14 17:50:07",
      "category": null
    },
    {
      "url": "https://www.huifabu.cn/haodan/163987.html",
      "text": "好单追觅S50增强版扫地机器人超薄上下水版 2308.68元06-14 17:47›",
      "source": "汇发部",
      "time": "2026-06-14 17:50:07",
      "category": null
    },
    {
      "url": "https://www.huifabu.cn/haodan/163986.html",
      "text": "好单十月结晶婴儿包单85*85cm 17.8元06-14 17:47›",
      "source": "汇发部",
      "time": "2026-06-14 17:50:07",
      "category": null
    },
    {
      "url": "https://www.huifabu.cn/weibochaohua/163985.html",
      "text": "超话kfm好价吗06-14 17:47›",
      "source": "汇发部",
      "time": "2026-06-14 17:50:07",
      "category": null
    },
    {
      "url": "https://www.huifabu.cn/haodan/163984.html",
      "text": "好单卡姿兰女士雾光粉饼定妆粉 赠粉扑 19.9元06-14 17:47›",
      "source": "汇发部",
      "time": "2026-06-14 17:50:07",
      "category": null
    },
    {
      "url": "https://www.huifabu.cn/weibochaohua/163983.html",
      "text": "超话冰袖06-14 17:46›",
      "source": "汇发部",
      "time": "2026-06-14 17:50:07",
      "category": null
    },
    {
      "url": "https://www.huifabu.cn/haodan/163982.html",
      "text": "好单桂格人参燕麦粉礼盒500g*2罐 26元06-14 17:46›",
      "source": "汇发部",
      "time": "2026-06-14 17:50:07",
      "category": null
    },
    {
      "url": "https://www.huifabu.cn/haodan/163981.html",
      "text": "好单思念云吞饺子合集任选10件 59元06-14 17:46›",
      "source": "汇发部",
      "time": "2026-06-14 17:50:07",
      "category": null
    },
    {
      "url": "https://www.huifabu.cn/weibo/163980.html",
      "text": "微博基诺浦儿童软底透气学步凉鞋 108.9元06-14 17:46›",
      "source": "汇发部",
      "time": "2026-06-14 17:50:07",
      "category": null
    },
    {
      "url": "https://www.huifabu.cn/haodan/163979.html",
      "text": "好单真真老老粽子礼盒8粽6味1180g 22.9元06-14 17:45›",
      "source": "汇发部",
      "time": "2026-06-14 17:50:07",
      "category": null
    },
    {
      "url": "https://www.huifabu.cn/haodan/163978.html",
      "text": "好单佳帮手海绵拖把28cm 1加厚棉头 14.8元，佳帮手免手洗平板拖把35cm 2块布 14.8元06-14 17:45›",
      "source": "汇发部",
      "time": "2026-06-14 17:50:07",
      "category": null
    },
    {
      "url": "https://www.huifabu.cn/weibochaohua/163977.html",
      "text": "超话请问你们知道xhs老活动吗06-14 17:45›",
      "source": "汇发部",
      "time": "2026-06-14 17:50:07",
      "category": null
    },
    {
      "url": "https://www.huifabu.cn/haodan/163976.html",
      "text": "好单京东plus年卡 39元06-14 17:44›",
      "source": "汇发部",
      "time": "2026-06-14 17:50:07",
      "category": "京东"
    },
    {
      "url": "https://www.huifabu.cn/zuankeba/163975.html",
      "text": "赚吧微信红包，江苏06-14 17:44›",
      "source": "汇发部",
      "time": "2026-06-14 17:50:07",
      "category": "红包"
    },
    {
      "url": "https://www.huifabu.cn/haodan/163974.html",
      "text": "好单飞鹤中老年多维奶粉700g*2 79元，飞鹤高钙多维奶粉700g*2 88元06-14 17:44›",
      "source": "汇发部",
      "time": "2026-06-14 17:50:07",
      "category": null
    },
    {
      "url": "https://www.huifabu.cn/haodan/163973.html",
      "text": "好单维他奶巧克力豆奶250ml*16盒 25.2元06-14 17:44›",
      "source": "汇发部",
      "time": "2026-06-14 17:50:07",
      "category": null
    },
    {
      "url": "https://www.huifabu.cn/xiaodigu/163972.html",
      "text": "嘀咕卡卡广东 下拉点二维码06-14 17:43›",
      "source": "汇发部",
      "time": "2026-06-14 17:50:07",
      "category": null
    },
    {
      "url": "https://www.huifabu.cn/haodan/163971.html",
      "text": "好单卡奇尔维D2磷葡钙片84片装 88.8元06-14 17:43›",
      "source": "汇发部",
      "time": "2026-06-14 17:50:07",
      "category": null
    },
    {
      "url": "https://www.huifabu.cn/zuankeba/163970.html",
      "text": "赚吧全返冰袖06-14 17:43›",
      "source": "汇发部",
      "time": "2026-06-14 17:50:07",
      "category": null
    },
    {
      "url": "https://www.huifabu.cn/haodan/163969.html",
      "text": "好单珀莱雅双抗精华100ml 189元06-14 17:43›",
      "source": "汇发部",
      "time": "2026-06-14 17:50:07",
      "category": null
    },
    {
      "url": "https://www.huifabu.cn/haodan/163968.html",
      "text": "好单领先鸭肉梨烘焙狗粮200g 6.9元06-14 17:42›",
      "source": "汇发部",
      "time": "2026-06-14 17:50:07",
      "category": null
    },
    {
      "url": "https://www.huifabu.cn/haodan/163967.html",
      "text": "好单云朵季大包抽纸5层400张*20包 24.9元06-14 17:42›",
      "source": "汇发部",
      "time": "2026-06-14 17:50:07",
      "category": null
    },
    {
      "url": "https://www.huifabu.cn/haodan/163966.html",
      "text": "好单乐比叮婴儿驱蚊喷雾100ml/瓶 19.8元06-14 17:42›",
      "source": "汇发部",
      "time": "2026-06-14 17:50:07",
      "category": null
    },
    {
      "url": "https://www.huifabu.cn/weibo/163965.html",
      "text": "微博1$v5zc5rmf60Y$:/ CZ6135 或复制淘囗令打开手机淘宝06-14 17:41›",
      "source": "汇发部",
      "time": "2026-06-14 17:50:07",
      "category": "淘宝"
    },
    {
      "url": "https://www.huifabu.cn/weibo/163964.html",
      "text": "微博敷尔佳白膜1片+绿膜1片 8.9元06-14 17:41›",
      "source": "汇发部",
      "time": "2026-06-14 17:50:07",
      "category": null
    },
    {
      "url": "https://www.huifabu.cn/weibo/163963.html",
      "text": "微博蔻驰老花波士顿包 1064-1110元06-14 17:40›",
      "source": "汇发部",
      "time": "2026-06-14 17:50:07",
      "category": null
    },
    {
      "url": "https://www.huifabu.cn/haodan/163962.html",
      "text": "好单超级恐龙系列套装6册 36元06-14 17:41›",
      "source": "汇发部",
      "time": "2026-06-14 17:50:07",
      "category": null
    },
    {
      "url": "https://www.huifabu.cn/haodan/163961.html",
      "text": "好单农家麻辣萝卜干260g*2罐 5.6元06-14 17:40›",
      "source": "汇发部",
      "time": "2026-06-14 17:50:07",
      "category": null
    },
    {
      "url": "https://www.huifabu.cn/haodan/163960.html",
      "text": "好单Sodolike抽绳垃圾袋100只双面2.4丝 3.99元06-14 17:40›",
      "source": "汇发部",
      "time": "2026-06-14 17:50:07",
      "category": null
    },
    {
      "url": "https://www.huifabu.cn/haodan/163959.html",
      "text": "好单艾美特手持小风扇 89元06-14 17:40›",
      "source": "汇发部",
      "time": "2026-06-14 17:50:07",
      "category": null
    },
    {
      "url": "https://www.huifabu.cn/haodan/163958.html",
      "text": "好单鲜京采原切鸡翅中2斤 买2件 84元06-14 17:39›",
      "source": "汇发部",
      "time": "2026-06-14 17:50:07",
      "category": null
    },
    {
      "url": "https://www.huifabu.cn/haodan/163957.html",
      "text": "好单怡思丁防晒喷雾100ml买一送一 60.05元，海蓝之谜焕新精萃水 2309元06-14 17:39›",
      "source": "汇发部",
      "time": "2026-06-14 17:50:07",
      "category": null
    },
    {
      "url": "https://www.huifabu.cn/haodan/163956.html",
      "text": "好单浅香氨基酸洗沐组合3件套 56元06-14 17:39›",
      "source": "汇发部",
      "time": "2026-06-14 17:50:07",
      "category": null
    },
    {
      "url": "https://www.huifabu.cn/haodan/163955.html",
      "text": "好单妮维雅保湿套装礼盒洁乳霜 103元06-14 17:39›",
      "source": "汇发部",
      "time": "2026-06-14 17:50:07",
      "category": null
    },
    {
      "url": "https://www.huifabu.cn/peiqi/163954.html",
      "text": "佩奇领航者小牛冰袖 拍下10 到货全饭 实付 0 问清楚客fu哈 防止反撸06-14 17:39›",
      "source": "汇发部",
      "time": "2026-06-14 17:50:07",
      "category": null
    },
    {
      "url": "https://www.huifabu.cn/weibochaohua/163953.html",
      "text": "超话好像没有姐妹发 买69.9套餐会送一张球星卡 这个球星卡有一个人的卡特别值💰06-14 17:38›",
      "source": "汇发部",
      "time": "2026-06-14 17:50:07",
      "category": null
    },
    {
      "url": "https://www.huifabu.cn/weibo/163952.html",
      "text": "微博欧莱雅安瓶面膜 5片 5元06-14 17:37›",
      "source": "汇发部",
      "time": "2026-06-14 17:50:07",
      "category": null
    },
    {
      "url": "https://www.zhuanyes.com/forum.php",
      "text": "版块BBS",
      "source": "专业线报",
      "time": "2026-06-14 17:50:07"
    },
    {
      "url": "https://www.zhuanyes.com/xianbao/xianbao-my.html",
      "text": "我的线报",
      "source": "专业线报",
      "time": "2026-06-14 17:50:07"
    },
    {
      "url": "https://www.zhuanyes.com/xianbao/haoquan-xianbao.html",
      "text": "神价白菜",
      "source": "专业线报",
      "time": "2026-06-14 17:50:07"
    },
    {
      "url": "https://www.zhuanyes.com/xianbao/member.php?mod=sign",
      "text": "立即注册",
      "source": "专业线报",
      "time": "2026-06-14 17:50:07"
    },
    {
      "url": "https://www.zhuanyes.com/forum-36-1.html",
      "text": "线报讨论",
      "source": "专业线报",
      "time": "2026-06-14 17:50:07"
    },
    {
      "url": "https://www.zhuanyes.com/forum-38-1.html",
      "text": "优惠分享",
      "source": "专业线报",
      "time": "2026-06-14 17:50:07"
    },
    {
      "url": "https://www.zhuanyes.com/xianbao/xianbao-my.html",
      "text": "我收藏的线报",
      "source": "专业线报",
      "time": "2026-06-14 17:50:07"
    },
    {
      "url": "https://www.zhuanyes.com/xianbao/xianbao-my.html?ac=part",
      "text": "我参与的线报",
      "source": "专业线报",
      "time": "2026-06-14 17:50:07"
    },
    {
      "url": "https://s.click.taobao.com/XfpJYel",
      "text": "淘宝618超级红包，最高26888元无门槛红包，每天都能领 >>>",
      "source": "专业线报",
      "time": "2026-06-14 17:50:07"
    },
    {
      "url": "https://u.jd.com/HDqz70W",
      "text": "京东618红包来了，最高26618元无门槛超级大红包，每天可以领三次 >>>",
      "source": "专业线报",
      "time": "2026-06-14 17:50:07"
    },
    {
      "url": "https://www.zhuanyes.com/xianbao/676666.html",
      "text": "每日必领：淘宝闪购+美团外卖+京东外卖红包",
      "source": "专业线报",
      "time": "2026-06-14 17:50:07"
    },
    {
      "url": "https://www.zhuanyes.com/xianbao/xianbao-day.html",
      "text": "24小时热门",
      "source": "专业线报",
      "time": "2026-06-14 17:50:07"
    },
    {
      "url": "https://www.zhuanyes.com/xianbao/xianbao-week.html",
      "text": "一周热门",
      "source": "专业线报",
      "time": "2026-06-14 17:50:07"
    },
    {
      "url": "https://www.zhuanyes.com/xianbao/699182.html",
      "text": "领航者小牛冰袖 拍下10 ，到货全饭 实付【0】",
      "source": "专业线报",
      "time": "2026-06-14 17:50:07",
      "category": null
    },
    {
      "url": "https://www.zhuanyes.com/xianbao/699181.html",
      "text": "斧头 洗洁精 1.18kg*2瓶",
      "source": "专业线报",
      "time": "2026-06-14 17:50:07",
      "category": null
    },
    {
      "url": "https://www.zhuanyes.com/xianbao/699180.html",
      "text": "姓名单位乱，题目对5，去抽",
      "source": "专业线报",
      "time": "2026-06-14 17:50:07",
      "category": null
    },
    {
      "url": "https://www.zhuanyes.com/xianbao/699179.html",
      "text": "速领哈 目前还有 叠加吃饭很香",
      "source": "专业线报",
      "time": "2026-06-14 17:50:07",
      "category": null
    },
    {
      "url": "https://www.zhuanyes.com/xianbao/699178.html",
      "text": "17点30分 补大量5-4叠加卷",
      "source": "专业线报",
      "time": "2026-06-14 17:50:07",
      "category": null
    },
    {
      "url": "https://www.zhuanyes.com/xianbao/699177.html",
      "text": "沪上阿姨 3款1元喝+幸运咖 八款1元喝+蜜雪 1元抢",
      "source": "专业线报",
      "time": "2026-06-14 17:50:07",
      "category": null
    },
    {
      "url": "https://www.zhuanyes.com/xianbao/699176.html",
      "text": "建行惠省钱湖南地区去看看，我3户湖南都出5折了，另外3户广东",
      "source": "专业线报",
      "time": "2026-06-14 17:50:07",
      "category": null
    },
    {
      "url": "https://www.zhuanyes.com/xianbao/699175.html",
      "text": "1.1🉐金丝菊花茶3g*5袋 ，(反复拍2箪，共发20袋)",
      "source": "专业线报",
      "time": "2026-06-14 17:50:07",
      "category": null
    },
    {
      "url": "https://www.zhuanyes.com/xianbao/699174.html",
      "text": "这个发财金块也可以，亲测一个多小时，到账16块多",
      "source": "专业线报",
      "time": "2026-06-14 17:50:07",
      "category": null
    },
    {
      "url": "https://www.zhuanyes.com/xianbao/699173.html",
      "text": "zfb搜【天猫】进xcx ，自动弹3k猫猫币 先拿 ​",
      "source": "专业线报",
      "time": "2026-06-14 17:50:07",
      "category": "淘宝"
    },
    {
      "url": "https://www.zhuanyes.com/xianbao/699172.html",
      "text": "新百伦情侣运动鞋券后69.9元",
      "source": "专业线报",
      "time": "2026-06-14 17:50:07",
      "category": "优惠券"
    },
    {
      "url": "https://www.zhuanyes.com/xianbao/699171.html",
      "text": "1⃣️京东10-19点 整点大牌1元",
      "source": "专业线报",
      "time": "2026-06-14 17:50:07",
      "category": "京东"
    },
    {
      "url": "https://www.zhuanyes.com/xianbao/699170.html",
      "text": "原文话费限制移动",
      "source": "专业线报",
      "time": "2026-06-14 17:50:07",
      "category": null
    },
    {
      "url": "https://www.zhuanyes.com/xianbao/699169.html",
      "text": "金典有水，刚中虹包",
      "source": "专业线报",
      "time": "2026-06-14 17:50:07",
      "category": "红包"
    },
    {
      "url": "https://www.zhuanyes.com/xianbao/699168.html",
      "text": "dy0.01亓精华霜1.8mlx3 ​",
      "source": "专业线报",
      "time": "2026-06-14 17:50:07",
      "category": null
    },
    {
      "url": "https://www.zhuanyes.com/xianbao/699167.html",
      "text": "5-4现在还有哈 不用组队 随便领",
      "source": "专业线报",
      "time": "2026-06-14 17:50:07"
    },
    {
      "url": "https://www.zhuanyes.com/xianbao/699166.html",
      "text": "点赞返回 有反馈中0.26💰",
      "source": "专业线报",
      "time": "2026-06-14 17:50:07"
    },
    {
      "url": "https://www.zhuanyes.com/xianbao/699165.html",
      "text": "16点30分 补大量5-4叠加卷",
      "source": "专业线报",
      "time": "2026-06-14 17:50:07"
    },
    {
      "url": "https://www.zhuanyes.com/xianbao/699164.html",
      "text": "参半酵素牙膏洁白亮白120g",
      "source": "专业线报",
      "time": "2026-06-14 17:50:07"
    },
    {
      "url": "https://www.zhuanyes.com/xianbao/699163.html",
      "text": "河南体彩，要地区河南",
      "source": "专业线报",
      "time": "2026-06-14 17:50:07"
    },
    {
      "url": "https://www.zhuanyes.com/xianbao/699162.html",
      "text": "古茗惊喜567 抽500张免单",
      "source": "专业线报",
      "time": "2026-06-14 17:50:07"
    },
    {
      "url": "https://www.zhuanyes.com/xianbao/699161.html",
      "text": "茶救星球 抽1份兔单试试 随机中",
      "source": "专业线报",
      "time": "2026-06-14 17:50:07"
    },
    {
      "url": "https://www.zhuanyes.com/xianbao/699160.html",
      "text": "杰士邦小雨伞🚗补了‼️ ，苻8-8.7🉐18只，按步骤去抇",
      "source": "专业线报",
      "time": "2026-06-14 17:50:07"
    },
    {
      "url": "https://www.zhuanyes.com/xianbao/699159.html",
      "text": "1.5💰星球杯20个 ，(反复拍2箪，送小勺子)",
      "source": "专业线报",
      "time": "2026-06-14 17:50:07"
    },
    {
      "url": "https://www.zhuanyes.com/xianbao/699158.html",
      "text": "拼多多超级红包，每天都能领🧧",
      "source": "专业线报",
      "time": "2026-06-14 17:50:07"
    },
    {
      "url": "https://www.zhuanyes.com/xianbao/699157.html",
      "text": "京东大家都在疯狂囤货 ，先来这里领自提1r",
      "source": "专业线报",
      "time": "2026-06-14 17:50:07"
    },
    {
      "url": "https://www.zhuanyes.com/xianbao/699156.html",
      "text": "快手涨金币很简单 你只要去商场搜索护肤品 浏览加购买付款输错",
      "source": "专业线报",
      "time": "2026-06-14 17:50:07"
    },
    {
      "url": "https://www.zhuanyes.com/xianbao/699155.html",
      "text": "旺仔抽看看 小反馈 ，V打开 旺仔 玩游戏≥400分",
      "source": "专业线报",
      "time": "2026-06-14 17:50:07"
    },
    {
      "url": "https://www.zhuanyes.com/xianbao/699154.html",
      "text": "京东0入小羊毛！ ，先领一个鸿包",
      "source": "专业线报",
      "time": "2026-06-14 17:50:07"
    },
    {
      "url": "https://www.zhuanyes.com/xianbao/699153.html",
      "text": "之前微博签到7天的可以领了，我两个号都是3块",
      "source": "专业线报",
      "time": "2026-06-14 17:50:07"
    },
    {
      "url": "https://www.zhuanyes.com/xianbao/member.php?mod=logging&action=login",
      "text": "签到连续天20人签到看排名",
      "source": "专业线报",
      "time": "2026-06-14 17:50:07"
    },
    {
      "url": "https://www.zhuanyes.com/xianbao/699131.html",
      "text": "1.1🉐金银花300ml*1瓶",
      "source": "专业线报",
      "time": "2026-06-14 17:50:07"
    },
    {
      "url": "https://www.zhuanyes.com/xianbao/699152.html",
      "text": "⏰15点 家电zbj专场 留意鸿包雨",
      "source": "专业线报",
      "time": "2026-06-14 17:50:07"
    },
    {
      "url": "https://www.zhuanyes.com/xianbao/699147.html",
      "text": "京东红包！也记得领取+打卡",
      "source": "专业线报",
      "time": "2026-06-14 17:50:07"
    },
    {
      "url": "https://www.zhuanyes.com/xianbao/699143.html",
      "text": "抓紧换号去 蜜雪圣代1块钱一个",
      "source": "专业线报",
      "time": "2026-06-14 17:50:07"
    },
    {
      "url": "https://www.zhuanyes.com/xianbao/699117.html",
      "text": "敷尔佳医‘用面膜绿膜2片💰4.9",
      "source": "专业线报",
      "time": "2026-06-14 17:50:07"
    },
    {
      "url": "https://www.zhuanyes.com/xianbao/699137.html",
      "text": "京东10-19点 整点大牌1元",
      "source": "专业线报",
      "time": "2026-06-14 17:50:07",
      "category": "京东"
    },
    {
      "url": "https://www.12345pro.com/article/927.html",
      "text": "一一兔头母亲大po忦一一 先领88",
      "source": "12345线报",
      "time": "2026-06-14 17:50:07"
    },
    {
      "url": "https://www.12345pro.com/article/926.html",
      "text": "还是我伶俐",
      "source": "12345线报",
      "time": "2026-06-14 17:50:07"
    },
    {
      "url": "https://www.12345pro.com/article/925.html",
      "text": "每日破零就靠可乐瓶盖",
      "source": "12345线报",
      "time": "2026-06-14 17:50:07"
    },
    {
      "url": "https://www.12345pro.com/article/924.html",
      "text": "农行省钱卡付款马上减金 不用二维码的办法 今年还有",
      "source": "12345线报",
      "time": "2026-06-14 17:50:07"
    },
    {
      "url": "https://www.12345pro.com/article/923.html",
      "text": "华为畅享90 Pro Max的重量为232克",
      "source": "12345线报",
      "time": "2026-06-14 17:50:07"
    },
    {
      "url": "https://www.12345pro.com/article/922.html",
      "text": "荃盛 粽子礼盒8粽5味4蛋1280g  43.9亓自营包邮；手工肉粽 *精",
      "source": "12345线报",
      "time": "2026-06-14 17:50:07"
    },
    {
      "url": "https://www.12345pro.com/article/920.html",
      "text": "蜜雪冰城冰激凌与柠檬水",
      "source": "12345线报",
      "time": "2026-06-14 17:50:07"
    },
    {
      "url": "https://www.12345pro.com/article/677.html",
      "text": "付款宝付款有礼领取5亓红包",
      "source": "12345线报",
      "time": "2026-06-14 17:50:07"
    },
    {
      "url": "https://www.12345pro.com/article/678.html",
      "text": "古茗邀3人助力抽0.9亓咖啡券",
      "source": "12345线报",
      "time": "2026-06-14 17:50:07"
    },
    {
      "url": "https://www.12345pro.com/article/679.html",
      "text": "京东部分用户1.8亓开省省卡",
      "source": "12345线报",
      "time": "2026-06-14 17:50:07"
    },
    {
      "url": "https://www.12345pro.com/article/584.html",
      "text": "度娘打车抽沪上阿姨饮品免单",
      "source": "12345线报",
      "time": "2026-06-14 17:50:07"
    },
    {
      "url": "https://www.12345pro.com/article/585.html",
      "text": "淘宝淘金币玩跳一跳领加抵金",
      "source": "12345线报",
      "time": "2026-06-14 17:50:07"
    },
    {
      "url": "https://www.12345pro.com/article/586.html",
      "text": "淘宝天天砸金蛋兑0.01亓实物",
      "source": "12345线报",
      "time": "2026-06-14 17:50:07"
    },
    {
      "url": "https://www.12345pro.com/article/587.html",
      "text": "农行抽随机折扣买5亓马上减金",
      "source": "12345线报",
      "time": "2026-06-14 17:50:07"
    },
    {
      "url": "https://www.12345pro.com/article/588.html",
      "text": "付款宝付款有礼瓜分千万红包",
      "source": "12345线报",
      "time": "2026-06-14 17:50:07"
    },
    {
      "url": "https://www.12345pro.com/article/589.html",
      "text": "沪上阿姨抽10万份饮品免单券",
      "source": "12345线报",
      "time": "2026-06-14 17:50:07"
    },
    {
      "url": "https://www.12345pro.com/article/590.html",
      "text": "网易云音乐领取7天黑胶VIP",
      "source": "12345线报",
      "time": "2026-06-14 17:50:07"
    },
    {
      "url": "https://www.12345pro.com/article/591.html",
      "text": "美团建行数币0.01亓买10亓券",
      "source": "12345线报",
      "time": "2026-06-14 17:50:07"
    },
    {
      "url": "https://www.12345pro.com/article/592.html",
      "text": "京东0.01撸恪本洗脸巾7抽/包",
      "source": "12345线报",
      "time": "2026-06-14 17:50:07"
    },
    {
      "url": "https://www.12345pro.com/article/593.html",
      "text": "新一期 高德地图里程抽奶茶券或VIP",
      "source": "12345线报",
      "time": "2026-06-14 17:50:07"
    },
    {
      "url": "https://www.12345pro.com/article/624.html",
      "text": "京东0.01双头棉签35支*2",
      "source": "12345线报",
      "time": "2026-06-14 17:50:07",
      "category": "京东"
    },
    {
      "url": "https://cjx8.com/?cat=0",
      "text": "全部线报",
      "source": "超级线报",
      "time": "2026-06-14 17:50:07"
    },
    {
      "url": "https://cjx8.com/?cat=9",
      "text": "豆瓣买组",
      "source": "超级线报",
      "time": "2026-06-14 17:50:07"
    },
    {
      "url": "https://cjx8.com/?cat=3",
      "text": "豆瓣拼组",
      "source": "超级线报",
      "time": "2026-06-14 17:50:07"
    },
    {
      "url": "https://cjx8.com/?cat=4",
      "text": "佩奇线报",
      "source": "超级线报",
      "time": "2026-06-14 17:50:07"
    },
    {
      "url": "https://cjx8.com/?cat=6",
      "text": "蘑菇小牙牙",
      "source": "超级线报",
      "time": "2026-06-14 17:50:07"
    },
    {
      "url": "https://cjx8.com/?cat=5",
      "text": "小屁屁找",
      "source": "超级线报",
      "time": "2026-06-14 17:50:07"
    },
    {
      "url": "https://cjx8.com/?cat=13",
      "text": "好心天天分享",
      "source": "超级线报",
      "time": "2026-06-14 17:50:07"
    },
    {
      "url": "https://cjx8.com/?cat=10",
      "text": "败家少女的日常",
      "source": "超级线报",
      "time": "2026-06-14 17:50:07"
    },
    {
      "url": "https://cjx8.com/?cat=18",
      "text": "丐帮羊毛日记",
      "source": "超级线报",
      "time": "2026-06-14 17:50:07"
    },
    {
      "url": "https://cjx8.com/?cat=19",
      "text": "优惠女孩的日常",
      "source": "超级线报",
      "time": "2026-06-14 17:50:07"
    },
    {
      "url": "https://cjx8.com/?cat=11",
      "text": "天涯花花的百宝袋",
      "source": "超级线报",
      "time": "2026-06-14 17:50:07"
    },
    {
      "url": "https://cjx8.com/?cat=12",
      "text": "白菜省钱君",
      "source": "超级线报",
      "time": "2026-06-14 17:50:07"
    },
    {
      "url": "https://cjx8.com/?cat=14",
      "text": "披着羊毛的魔鬼",
      "source": "超级线报",
      "time": "2026-06-14 17:50:07"
    },
    {
      "url": "https://cjx8.com/?cat=17",
      "text": "妖娆本娆",
      "source": "超级线报",
      "time": "2026-06-14 17:50:07"
    },
    {
      "url": "https://cjx8.com/?cat=20",
      "text": "白给王酸菜",
      "source": "超级线报",
      "time": "2026-06-14 17:50:07"
    },
    {
      "url": "https://cjx8.com/?cat=21",
      "text": "拼夕夕bot",
      "source": "超级线报",
      "time": "2026-06-14 17:50:07"
    },
    {
      "url": "https://cjx8.com/?cat=22",
      "text": "光芒呀shine",
      "source": "超级线报",
      "time": "2026-06-14 17:50:07"
    },
    {
      "url": "https://cjx8.com/?cat=23",
      "text": "买白菜的妹妹",
      "source": "超级线报",
      "time": "2026-06-14 17:50:07"
    },
    {
      "url": "https://cjx8.com/?cat=24",
      "text": "薅羊毛的大队长",
      "source": "超级线报",
      "time": "2026-06-14 17:50:07"
    },
    {
      "url": "https://cjx8.com/post/1752186",
      "text": "光维他柠檬茶饮料500ml*15瓶，叠加优惠价48.9元2026-06-14 17:24:420淘宝菜花园新疆冰淇淋酸奶1KG*4桶到手75.8元，折9.4/斤2026-06-14 17:24:150京东",
      "source": "超级线报",
      "time": "2026-06-14 17:50:07",
      "category": "京东"
    },
    {
      "url": "https://cjx8.com/post/1752189",
      "text": "菜花园新疆冰淇淋酸奶1KG*4桶到手75.8元，折9.4/斤2026-06-14 17:24:150京东",
      "source": "超级线报",
      "time": "2026-06-14 17:50:07",
      "category": "京东"
    },
    {
      "url": "https://beian.miit.gov.cn/",
      "text": "闽ICP备2024062941号",
      "source": "超级线报",
      "time": "2026-06-14 17:50:07"
    },
    {
      "url": "https://nav.weyondesign.com",
      "text": "自贡PPT制作",
      "source": "超级线报",
      "time": "2026-06-14 17:50:07"
    },
    {
      "url": "http://www.yiyazaojiao.com",
      "text": "动画片下载",
      "source": "超级线报",
      "time": "2026-06-14 17:50:07"
    },
    {
      "url": "https://www.downext.com",
      "text": "次世代下载网",
      "source": "超级线报",
      "time": "2026-06-14 17:50:07"
    },
    {
      "url": "https://www.1haogu.com",
      "text": "学习资料",
      "source": "超级线报",
      "time": "2026-06-14 17:50:07"
    },
    {
      "url": "https://www.miao333.com",
      "text": "喵闪视觉",
      "source": "超级线报",
      "time": "2026-06-14 17:50:07"
    },
    {
      "url": "http://www.jincong.net",
      "text": "金聪线报",
      "source": "超级线报",
      "time": "2026-06-14 17:50:07"
    },
    {
      "url": "https://cjx8.com/sitemap/index.xml",
      "text": "站点地图",
      "source": "超级线报",
      "time": "2026-06-14 17:50:07"
    },
    {
      "url": "https://cjx8.com/feedback",
      "text": "申请友链",
      "source": "超级线报",
      "time": "2026-06-14 17:50:07"
    },
    {
      "url": "https://xianbao.icu/article/detail/404249",
      "text": "世界杯活动汇总",
      "source": "线报ICU",
      "time": "2026-06-14 17:50:07"
    },
    {
      "url": "https://u.jd.com/H1OZHtR",
      "text": "京东红包",
      "source": "线报ICU",
      "time": "2026-06-14 17:50:07"
    },
    {
      "url": "https://m.tb.cn/h.RblLFQy",
      "text": "淘宝红包",
      "source": "线报ICU",
      "time": "2026-06-14 17:50:07"
    },
    {
      "url": "https://xianbao.icu/article/detail/348793",
      "text": "活动推荐",
      "source": "线报ICU",
      "time": "2026-06-14 17:50:07"
    },
    {
      "url": "https://xianbao.icu/xianbao/detail/411137",
      "text": "美团-闪购-底部 抢神券 ⏰11:00 15:00 16:00 17:00 18:00 19:00 ...",
      "source": "线报ICU",
      "time": "2026-06-14 17:50:07",
      "category": "外卖"
    },
    {
      "url": "https://xianbao.icu/xianbao/wb?author=头号情报站",
      "text": "头号情报站",
      "source": "线报ICU",
      "time": "2026-06-14 17:50:07"
    },
    {
      "url": "https://xianbao.icu/xianbao/detail/411136",
      "text": "⏰️8-23点横幅 整点抢29-20券 💖丐友京东搜：按时吃饭 🔗 ❗️10点30/11点30/5-...",
      "source": "线报ICU",
      "time": "2026-06-14 17:50:07",
      "category": "京东"
    },
    {
      "url": "https://xianbao.icu/xianbao/wb?author=丐帮羊毛日记",
      "text": "丐帮羊毛日记",
      "source": "线报ICU",
      "time": "2026-06-14 17:50:07"
    },
    {
      "url": "https://xianbao.icu/xianbao/detail/411135",
      "text": "⏰18:00 美妆会场低价眇 ⏰18:00 京东医疗五折券 - ⏰18:00 京东搜【每日秒送】 可...",
      "source": "线报ICU",
      "time": "2026-06-14 17:50:07",
      "category": "京东"
    },
    {
      "url": "https://xianbao.icu/xianbao/detail/411134",
      "text": "V打开⏰10:00 15:00 18:00 瑞幸抢1w份9.9买一送一 #小程序://瑞幸咖啡/UH...",
      "source": "线报ICU",
      "time": "2026-06-14 17:50:07",
      "category": null
    },
    {
      "url": "https://xianbao.icu/xianbao/detail/411133",
      "text": "❗美团 华莱士兔单 06.14截 ⏰11:00 12:00 13:00 17:00 ⏰18:00 1...",
      "source": "线报ICU",
      "time": "2026-06-14 17:50:07",
      "category": "外卖"
    },
    {
      "url": "https://xianbao.icu/xianbao/detail/411132",
      "text": "18点 美团底部抽青岛/歪马18‼️ ⭐来听语音就行 抽出来更及时 YY语音搜【1423291848...",
      "source": "线报ICU",
      "time": "2026-06-14 17:50:07",
      "category": "外卖"
    },
    {
      "url": "https://xianbao.icu/xianbao/wb?author=佩奇线报",
      "text": "佩奇线报",
      "source": "线报ICU",
      "time": "2026-06-14 17:50:07"
    },
    {
      "url": "https://xianbao.icu/xianbao/detail/411131",
      "text": "⏰10点/12/14/16/18点/20点 美团搜：万物888 美团搜：万物免单 神券16-16，3...",
      "source": "线报ICU",
      "time": "2026-06-14 17:50:07",
      "category": "外卖"
    },
    {
      "url": "https://xianbao.icu/xianbao/detail/411130",
      "text": "快‼️39💰京東plus年卡 自测，不同号送的红包不同 1️⃣先收臧浏览不𢫦 2️⃣跳αpp商品加入...",
      "source": "线报ICU",
      "time": "2026-06-14 17:50:07",
      "category": "红包"
    },
    {
      "url": "https://xianbao.icu/xianbao/detail/411129",
      "text": "微信红包，江苏",
      "source": "线报ICU",
      "time": "2026-06-14 17:50:07",
      "category": "红包"
    },
    {
      "url": "https://xianbao.icu/xianbao/zkb?author=白菜人人",
      "text": "白菜人人",
      "source": "线报ICU",
      "time": "2026-06-14 17:50:07",
      "category": null
    },
    {
      "url": "https://xianbao.icu/xianbao/detail/411128",
      "text": "‼丐友淘宝搜：天天领幸运 1$BtNM5qIMjFO$:/ CA1710 这个分xiang领的鸿包是...",
      "source": "线报ICU",
      "time": "2026-06-14 17:50:07",
      "category": "淘宝"
    },
    {
      "url": "https://xianbao.icu/xianbao/detail/411127",
      "text": "日常 出行打车记得领倦哈 - 滴滴打车每天最高5折打车券 👉 花小猪每天领2~10亓打车券 👉...",
      "source": "线报ICU",
      "time": "2026-06-14 17:50:07",
      "category": "优惠券"
    },
    {
      "url": "https://xianbao.icu/xianbao/detail/411126",
      "text": "卡卡广东 下拉点二维码",
      "source": "线报ICU",
      "time": "2026-06-14 17:50:07",
      "category": null
    },
    {
      "url": "https://xianbao.icu/xianbao/detail/411125",
      "text": "全返冰袖",
      "source": "线报ICU",
      "time": "2026-06-14 17:50:07",
      "category": null
    },
    {
      "url": "https://xianbao.icu/xianbao/zkb?author=pk1223",
      "text": "pk1223",
      "source": "线报ICU",
      "time": "2026-06-14 17:50:07",
      "category": null
    },
    {
      "url": "https://xianbao.icu/xianbao/detail/411124",
      "text": "把想买的东西加购即可领礼金 丐友淘宝αpp搜：幸运购物车 1$v5zc5rmf60Y$:/ CZ61...",
      "source": "线报ICU",
      "time": "2026-06-14 17:50:07",
      "category": "淘宝"
    },
    {
      "url": "https://xianbao.icu/xianbao/detail/411123",
      "text": "这个店也有0亓购，到货返的 领航者小牛 冰袖， 拍下10，到货全返 实付💰0...",
      "source": "线报ICU",
      "time": "2026-06-14 17:50:07",
      "category": null
    },
    {
      "url": "https://xianbao.icu/xianbao/detail/411122",
      "text": "领航者小牛冰袖 拍下10 到货全饭 实付【0】 问清楚客fu哈 防止反撸 - 右下角领鸿包叠加...",
      "source": "线报ICU",
      "time": "2026-06-14 17:50:07",
      "category": "红包"
    },
    {
      "url": "https://xianbao.icu/xianbao/detail/411121",
      "text": "能买吗？会亏吗",
      "source": "线报ICU",
      "time": "2026-06-14 17:50:07",
      "category": null
    },
    {
      "url": "https://xianbao.icu/xianbao/xdg?author=爱情很刺眼",
      "text": "爱情很刺眼",
      "source": "线报ICU",
      "time": "2026-06-14 17:50:07",
      "category": null
    },
    {
      "url": "https://xianbao.icu/xianbao/detail/411120",
      "text": "这个店也有0元购，到货返的，看需 领航者小牛 冰袖，拍下10，到货全返，实付【0】...",
      "source": "线报ICU",
      "time": "2026-06-14 17:50:07",
      "category": null
    },
    {
      "url": "https://xianbao.icu/xianbao/wb?author=光芒呀shine",
      "text": "光芒呀shine",
      "source": "线报ICU",
      "time": "2026-06-14 17:50:07"
    },
    {
      "url": "https://xianbao.icu/xianbao/detail/411119",
      "text": "斧头 洗洁精 1.18kg*2瓶 右上角“…”进惍币，v1p💰13.5...",
      "source": "线报ICU",
      "time": "2026-06-14 17:50:07",
      "category": null
    }
  ],
  "updated_at": "2026-06-14 17:50:07"
}